{
	"textures": [
		{
			"image": "textureAtlasOne.png",
			"format": "RGBA8888",
			"size": {
				"w": 1016,
				"h": 243
			},
			"scale": 1,
			"frames": [
				{
					"filename": "Whirl",
					"rotated": false,
					"trimmed": false,
					"sourceSize": {
						"w": 720,
						"h": 45
					},
					"spriteSourceSize": {
						"x": 0,
						"y": 0,
						"w": 720,
						"h": 45
					},
					"frame": {
						"x": 1,
						"y": 1,
						"w": 720,
						"h": 45
					}
				},
				{
					"filename": "BlackFlowingDown",
					"rotated": false,
					"trimmed": false,
					"sourceSize": {
						"w": 480,
						"h": 32
					},
					"spriteSourceSize": {
						"x": 0,
						"y": 0,
						"w": 480,
						"h": 32
					},
					"frame": {
						"x": 1,
						"y": 48,
						"w": 480,
						"h": 32
					}
				},
				{
					"filename": "chest",
					"rotated": false,
					"trimmed": false,
					"sourceSize": {
						"w": 368,
						"h": 43
					},
					"spriteSourceSize": {
						"x": 0,
						"y": 0,
						"w": 368,
						"h": 43
					},
					"frame": {
						"x": 1,
						"y": 82,
						"w": 368,
						"h": 43
					}
				},
				{
					"filename": "flamingGoose",
					"rotated": false,
					"trimmed": false,
					"sourceSize": {
						"w": 328,
						"h": 79
					},
					"spriteSourceSize": {
						"x": 0,
						"y": 0,
						"w": 328,
						"h": 79
					},
					"frame": {
						"x": 1,
						"y": 127,
						"w": 328,
						"h": 79
					}
				},
				{
					"filename": "quasar",
					"rotated": false,
					"trimmed": false,
					"sourceSize": {
						"w": 288,
						"h": 16
					},
					"spriteSourceSize": {
						"x": 0,
						"y": 0,
						"w": 288,
						"h": 16
					},
					"frame": {
						"x": 723,
						"y": 1,
						"w": 288,
						"h": 16
					}
				},
				{
					"filename": "BlueWaterEastShore",
					"rotated": false,
					"trimmed": false,
					"sourceSize": {
						"w": 256,
						"h": 16
					},
					"spriteSourceSize": {
						"x": 0,
						"y": 0,
						"w": 256,
						"h": 16
					},
					"frame": {
						"x": 1,
						"y": 208,
						"w": 256,
						"h": 16
					}
				},
				{
					"filename": "BlueWaterNorthEastShore",
					"rotated": false,
					"trimmed": false,
					"sourceSize": {
						"w": 256,
						"h": 16
					},
					"spriteSourceSize": {
						"x": 0,
						"y": 0,
						"w": 256,
						"h": 16
					},
					"frame": {
						"x": 1,
						"y": 226,
						"w": 256,
						"h": 16
					}
				},
				{
					"filename": "BlueWaterNorthShore",
					"rotated": false,
					"trimmed": false,
					"sourceSize": {
						"w": 256,
						"h": 16
					},
					"spriteSourceSize": {
						"x": 0,
						"y": 0,
						"w": 256,
						"h": 16
					},
					"frame": {
						"x": 723,
						"y": 19,
						"w": 256,
						"h": 16
					}
				},
				{
					"filename": "BlueWaterNorthWestShore",
					"rotated": false,
					"trimmed": false,
					"sourceSize": {
						"w": 256,
						"h": 16
					},
					"spriteSourceSize": {
						"x": 0,
						"y": 0,
						"w": 256,
						"h": 16
					},
					"frame": {
						"x": 723,
						"y": 37,
						"w": 256,
						"h": 16
					}
				},
				{
					"filename": "Fountain",
					"rotated": false,
					"trimmed": false,
					"sourceSize": {
						"w": 176,
						"h": 16
					},
					"spriteSourceSize": {
						"x": 0,
						"y": 0,
						"w": 176,
						"h": 16
					},
					"frame": {
						"x": 483,
						"y": 48,
						"w": 176,
						"h": 16
					}
				},
				{
					"filename": "BlueWaterNorthWestShoreCorner",
					"rotated": false,
					"trimmed": false,
					"sourceSize": {
						"w": 256,
						"h": 16
					},
					"spriteSourceSize": {
						"x": 0,
						"y": 0,
						"w": 256,
						"h": 16
					},
					"frame": {
						"x": 661,
						"y": 55,
						"w": 256,
						"h": 16
					}
				},
				{
					"filename": "laserArrow",
					"rotated": false,
					"trimmed": false,
					"sourceSize": {
						"w": 160,
						"h": 16
					},
					"spriteSourceSize": {
						"x": 0,
						"y": 0,
						"w": 160,
						"h": 16
					},
					"frame": {
						"x": 483,
						"y": 66,
						"w": 160,
						"h": 16
					}
				},
				{
					"filename": "BlueWaterSouthEastShore",
					"rotated": false,
					"trimmed": false,
					"sourceSize": {
						"w": 256,
						"h": 16
					},
					"spriteSourceSize": {
						"x": 0,
						"y": 0,
						"w": 256,
						"h": 16
					},
					"frame": {
						"x": 645,
						"y": 73,
						"w": 256,
						"h": 16
					}
				},
				{
					"filename": "BlueWaterSouthEastShoreCorner",
					"rotated": false,
					"trimmed": false,
					"sourceSize": {
						"w": 256,
						"h": 16
					},
					"spriteSourceSize": {
						"x": 0,
						"y": 0,
						"w": 256,
						"h": 16
					},
					"frame": {
						"x": 371,
						"y": 84,
						"w": 256,
						"h": 16
					}
				},
				{
					"filename": "BlueWaterSouthShore",
					"rotated": false,
					"trimmed": false,
					"sourceSize": {
						"w": 256,
						"h": 16
					},
					"spriteSourceSize": {
						"x": 0,
						"y": 0,
						"w": 256,
						"h": 16
					},
					"frame": {
						"x": 371,
						"y": 102,
						"w": 256,
						"h": 16
					}
				},
				{
					"filename": "BlueWaterSouthWestShore",
					"rotated": false,
					"trimmed": false,
					"sourceSize": {
						"w": 256,
						"h": 16
					},
					"spriteSourceSize": {
						"x": 0,
						"y": 0,
						"w": 256,
						"h": 16
					},
					"frame": {
						"x": 371,
						"y": 120,
						"w": 256,
						"h": 16
					}
				},
				{
					"filename": "BlueWaterSouthWestShoreCorner",
					"rotated": false,
					"trimmed": false,
					"sourceSize": {
						"w": 256,
						"h": 16
					},
					"spriteSourceSize": {
						"x": 0,
						"y": 0,
						"w": 256,
						"h": 16
					},
					"frame": {
						"x": 629,
						"y": 91,
						"w": 256,
						"h": 16
					}
				},
				{
					"filename": "BlueWaterWestShore",
					"rotated": false,
					"trimmed": false,
					"sourceSize": {
						"w": 256,
						"h": 16
					},
					"spriteSourceSize": {
						"x": 0,
						"y": 0,
						"w": 256,
						"h": 16
					},
					"frame": {
						"x": 629,
						"y": 109,
						"w": 256,
						"h": 16
					}
				},
				{
					"filename": "PurpleRunningRunes",
					"rotated": false,
					"trimmed": false,
					"sourceSize": {
						"w": 256,
						"h": 16
					},
					"spriteSourceSize": {
						"x": 0,
						"y": 0,
						"w": 256,
						"h": 16
					},
					"frame": {
						"x": 629,
						"y": 127,
						"w": 256,
						"h": 16
					}
				},
				{
					"filename": "bloomby",
					"rotated": false,
					"trimmed": false,
					"sourceSize": {
						"w": 240,
						"h": 16
					},
					"spriteSourceSize": {
						"x": 0,
						"y": 0,
						"w": 240,
						"h": 16
					},
					"frame": {
						"x": 331,
						"y": 138,
						"w": 240,
						"h": 16
					}
				},
				{
					"filename": "litSmoke",
					"rotated": false,
					"trimmed": false,
					"sourceSize": {
						"w": 128,
						"h": 128
					},
					"spriteSourceSize": {
						"x": 0,
						"y": 0,
						"w": 128,
						"h": 128
					},
					"frame": {
						"x": 887,
						"y": 91,
						"w": 128,
						"h": 128
					}
				},
				{
					"filename": "writtenPaper",
					"rotated": false,
					"trimmed": false,
					"sourceSize": {
						"w": 154,
						"h": 14
					},
					"spriteSourceSize": {
						"x": 0,
						"y": 0,
						"w": 154,
						"h": 14
					},
					"frame": {
						"x": 331,
						"y": 156,
						"w": 154,
						"h": 14
					}
				},
				{
					"filename": "MountainWallSparkleTwo",
					"rotated": false,
					"trimmed": false,
					"sourceSize": {
						"w": 144,
						"h": 16
					},
					"spriteSourceSize": {
						"x": 0,
						"y": 0,
						"w": 144,
						"h": 16
					},
					"frame": {
						"x": 331,
						"y": 172,
						"w": 144,
						"h": 16
					}
				},
				{
					"filename": "SilverSparkleForTree",
					"rotated": false,
					"trimmed": false,
					"sourceSize": {
						"w": 144,
						"h": 16
					},
					"spriteSourceSize": {
						"x": 0,
						"y": 0,
						"w": 144,
						"h": 16
					},
					"frame": {
						"x": 331,
						"y": 190,
						"w": 144,
						"h": 16
					}
				},
				{
					"filename": "BlackWater",
					"rotated": false,
					"trimmed": false,
					"sourceSize": {
						"w": 128,
						"h": 16
					},
					"spriteSourceSize": {
						"x": 0,
						"y": 0,
						"w": 128,
						"h": 16
					},
					"frame": {
						"x": 259,
						"y": 208,
						"w": 128,
						"h": 16
					}
				},
				{
					"filename": "BlueWater",
					"rotated": false,
					"trimmed": false,
					"sourceSize": {
						"w": 128,
						"h": 16
					},
					"spriteSourceSize": {
						"x": 0,
						"y": 0,
						"w": 128,
						"h": 16
					},
					"frame": {
						"x": 259,
						"y": 226,
						"w": 128,
						"h": 16
					}
				},
				{
					"filename": "GroundSparkleOne",
					"rotated": false,
					"trimmed": false,
					"sourceSize": {
						"w": 96,
						"h": 16
					},
					"spriteSourceSize": {
						"x": 0,
						"y": 0,
						"w": 96,
						"h": 16
					},
					"frame": {
						"x": 903,
						"y": 73,
						"w": 96,
						"h": 16
					}
				},
				{
					"filename": "GroundSparkleTwo",
					"rotated": false,
					"trimmed": false,
					"sourceSize": {
						"w": 96,
						"h": 16
					},
					"spriteSourceSize": {
						"x": 0,
						"y": 0,
						"w": 96,
						"h": 16
					},
					"frame": {
						"x": 919,
						"y": 55,
						"w": 96,
						"h": 16
					}
				},
				{
					"filename": "BlueWaterFlowingDown",
					"rotated": false,
					"trimmed": false,
					"sourceSize": {
						"w": 128,
						"h": 16
					},
					"spriteSourceSize": {
						"x": 0,
						"y": 0,
						"w": 128,
						"h": 16
					},
					"frame": {
						"x": 389,
						"y": 208,
						"w": 128,
						"h": 16
					}
				},
				{
					"filename": "RainbowTileOne",
					"rotated": false,
					"trimmed": false,
					"sourceSize": {
						"w": 128,
						"h": 16
					},
					"spriteSourceSize": {
						"x": 0,
						"y": 0,
						"w": 128,
						"h": 16
					},
					"frame": {
						"x": 389,
						"y": 226,
						"w": 128,
						"h": 16
					}
				},
				{
					"filename": "MountainWallSparkleOne",
					"rotated": false,
					"trimmed": false,
					"sourceSize": {
						"w": 80,
						"h": 16
					},
					"spriteSourceSize": {
						"x": 0,
						"y": 0,
						"w": 80,
						"h": 16
					},
					"frame": {
						"x": 487,
						"y": 156,
						"w": 80,
						"h": 16
					}
				},
				{
					"filename": "WickedSnailOne",
					"rotated": false,
					"trimmed": false,
					"sourceSize": {
						"w": 32,
						"h": 32
					},
					"spriteSourceSize": {
						"x": 0,
						"y": 0,
						"w": 32,
						"h": 32
					},
					"frame": {
						"x": 477,
						"y": 174,
						"w": 32,
						"h": 32
					}
				},
				{
					"filename": "SkullWink",
					"rotated": false,
					"trimmed": false,
					"sourceSize": {
						"w": 64,
						"h": 16
					},
					"spriteSourceSize": {
						"x": 0,
						"y": 0,
						"w": 64,
						"h": 16
					},
					"frame": {
						"x": 511,
						"y": 174,
						"w": 64,
						"h": 16
					}
				},
				{
					"filename": "blackTankSingle",
					"rotated": false,
					"trimmed": false,
					"sourceSize": {
						"w": 46,
						"h": 38
					},
					"spriteSourceSize": {
						"x": 0,
						"y": 0,
						"w": 46,
						"h": 38
					},
					"frame": {
						"x": 519,
						"y": 192,
						"w": 46,
						"h": 38
					}
				},
				{
					"filename": "blueTankSingle",
					"rotated": false,
					"trimmed": false,
					"sourceSize": {
						"w": 46,
						"h": 38
					},
					"spriteSourceSize": {
						"x": 0,
						"y": 0,
						"w": 46,
						"h": 38
					},
					"frame": {
						"x": 577,
						"y": 138,
						"w": 46,
						"h": 38
					}
				},
				{
					"filename": "darkBlueTankSingle",
					"rotated": false,
					"trimmed": false,
					"sourceSize": {
						"w": 46,
						"h": 38
					},
					"spriteSourceSize": {
						"x": 0,
						"y": 0,
						"w": 46,
						"h": 38
					},
					"frame": {
						"x": 625,
						"y": 145,
						"w": 46,
						"h": 38
					}
				},
				{
					"filename": "greyTankSingle",
					"rotated": false,
					"trimmed": false,
					"sourceSize": {
						"w": 46,
						"h": 38
					},
					"spriteSourceSize": {
						"x": 0,
						"y": 0,
						"w": 46,
						"h": 38
					},
					"frame": {
						"x": 673,
						"y": 145,
						"w": 46,
						"h": 38
					}
				},
				{
					"filename": "lightBlueTankSingle",
					"rotated": false,
					"trimmed": false,
					"sourceSize": {
						"w": 46,
						"h": 38
					},
					"spriteSourceSize": {
						"x": 0,
						"y": 0,
						"w": 46,
						"h": 38
					},
					"frame": {
						"x": 721,
						"y": 145,
						"w": 46,
						"h": 38
					}
				},
				{
					"filename": "orangeTankSingle",
					"rotated": false,
					"trimmed": false,
					"sourceSize": {
						"w": 46,
						"h": 38
					},
					"spriteSourceSize": {
						"x": 0,
						"y": 0,
						"w": 46,
						"h": 38
					},
					"frame": {
						"x": 769,
						"y": 145,
						"w": 46,
						"h": 38
					}
				},
				{
					"filename": "pinkTankSingle",
					"rotated": false,
					"trimmed": false,
					"sourceSize": {
						"w": 46,
						"h": 38
					},
					"spriteSourceSize": {
						"x": 0,
						"y": 0,
						"w": 46,
						"h": 38
					},
					"frame": {
						"x": 817,
						"y": 145,
						"w": 46,
						"h": 38
					}
				},
				{
					"filename": "purpleTankSingle",
					"rotated": false,
					"trimmed": false,
					"sourceSize": {
						"w": 46,
						"h": 38
					},
					"spriteSourceSize": {
						"x": 0,
						"y": 0,
						"w": 46,
						"h": 38
					},
					"frame": {
						"x": 577,
						"y": 178,
						"w": 46,
						"h": 38
					}
				},
				{
					"filename": "redTankSingle",
					"rotated": false,
					"trimmed": false,
					"sourceSize": {
						"w": 46,
						"h": 38
					},
					"spriteSourceSize": {
						"x": 0,
						"y": 0,
						"w": 46,
						"h": 38
					},
					"frame": {
						"x": 625,
						"y": 185,
						"w": 46,
						"h": 38
					}
				},
				{
					"filename": "turquoiseTankSingle",
					"rotated": false,
					"trimmed": false,
					"sourceSize": {
						"w": 46,
						"h": 38
					},
					"spriteSourceSize": {
						"x": 0,
						"y": 0,
						"w": 46,
						"h": 38
					},
					"frame": {
						"x": 673,
						"y": 185,
						"w": 46,
						"h": 38
					}
				},
				{
					"filename": "yellowTankSingle",
					"rotated": false,
					"trimmed": false,
					"sourceSize": {
						"w": 46,
						"h": 38
					},
					"spriteSourceSize": {
						"x": 0,
						"y": 0,
						"w": 46,
						"h": 38
					},
					"frame": {
						"x": 721,
						"y": 185,
						"w": 46,
						"h": 38
					}
				},
				{
					"filename": "TableOne",
					"rotated": false,
					"trimmed": false,
					"sourceSize": {
						"w": 16,
						"h": 10
					},
					"spriteSourceSize": {
						"x": 0,
						"y": 0,
						"w": 16,
						"h": 10
					},
					"frame": {
						"x": 519,
						"y": 232,
						"w": 16,
						"h": 10
					}
				},
				{
					"filename": "ChairTwo",
					"rotated": false,
					"trimmed": false,
					"sourceSize": {
						"w": 30,
						"h": 12
					},
					"spriteSourceSize": {
						"x": 0,
						"y": 0,
						"w": 30,
						"h": 12
					},
					"frame": {
						"x": 981,
						"y": 19,
						"w": 30,
						"h": 12
					}
				},
				{
					"filename": "Barricade-BlackKey",
					"rotated": false,
					"trimmed": false,
					"sourceSize": {
						"w": 16,
						"h": 16
					},
					"spriteSourceSize": {
						"x": 0,
						"y": 0,
						"w": 16,
						"h": 16
					},
					"frame": {
						"x": 865,
						"y": 145,
						"w": 16,
						"h": 16
					}
				},
				{
					"filename": "Barricade-BlueKey",
					"rotated": false,
					"trimmed": false,
					"sourceSize": {
						"w": 16,
						"h": 16
					},
					"spriteSourceSize": {
						"x": 0,
						"y": 0,
						"w": 16,
						"h": 16
					},
					"frame": {
						"x": 769,
						"y": 185,
						"w": 16,
						"h": 16
					}
				},
				{
					"filename": "Barricade-DarkBlueKey",
					"rotated": false,
					"trimmed": false,
					"sourceSize": {
						"w": 16,
						"h": 16
					},
					"spriteSourceSize": {
						"x": 0,
						"y": 0,
						"w": 16,
						"h": 16
					},
					"frame": {
						"x": 981,
						"y": 33,
						"w": 16,
						"h": 16
					}
				},
				{
					"filename": "Barricade-GreyKey",
					"rotated": false,
					"trimmed": false,
					"sourceSize": {
						"w": 16,
						"h": 16
					},
					"spriteSourceSize": {
						"x": 0,
						"y": 0,
						"w": 16,
						"h": 16
					},
					"frame": {
						"x": 999,
						"y": 33,
						"w": 16,
						"h": 16
					}
				},
				{
					"filename": "Barricade-LightBlueKey",
					"rotated": false,
					"trimmed": false,
					"sourceSize": {
						"w": 16,
						"h": 16
					},
					"spriteSourceSize": {
						"x": 0,
						"y": 0,
						"w": 16,
						"h": 16
					},
					"frame": {
						"x": 865,
						"y": 163,
						"w": 16,
						"h": 16
					}
				},
				{
					"filename": "Barricade-OrangeKey",
					"rotated": false,
					"trimmed": false,
					"sourceSize": {
						"w": 16,
						"h": 16
					},
					"spriteSourceSize": {
						"x": 0,
						"y": 0,
						"w": 16,
						"h": 16
					},
					"frame": {
						"x": 769,
						"y": 203,
						"w": 16,
						"h": 16
					}
				},
				{
					"filename": "Barricade-PinkKey",
					"rotated": false,
					"trimmed": false,
					"sourceSize": {
						"w": 16,
						"h": 16
					},
					"spriteSourceSize": {
						"x": 0,
						"y": 0,
						"w": 16,
						"h": 16
					},
					"frame": {
						"x": 787,
						"y": 185,
						"w": 16,
						"h": 16
					}
				},
				{
					"filename": "Barricade-PurpleKey",
					"rotated": false,
					"trimmed": false,
					"sourceSize": {
						"w": 16,
						"h": 16
					},
					"spriteSourceSize": {
						"x": 0,
						"y": 0,
						"w": 16,
						"h": 16
					},
					"frame": {
						"x": 787,
						"y": 203,
						"w": 16,
						"h": 16
					}
				},
				{
					"filename": "Barricade-RedKey",
					"rotated": false,
					"trimmed": false,
					"sourceSize": {
						"w": 16,
						"h": 16
					},
					"spriteSourceSize": {
						"x": 0,
						"y": 0,
						"w": 16,
						"h": 16
					},
					"frame": {
						"x": 805,
						"y": 185,
						"w": 16,
						"h": 16
					}
				},
				{
					"filename": "Barricade-TurquoiseKey",
					"rotated": false,
					"trimmed": false,
					"sourceSize": {
						"w": 16,
						"h": 16
					},
					"spriteSourceSize": {
						"x": 0,
						"y": 0,
						"w": 16,
						"h": 16
					},
					"frame": {
						"x": 805,
						"y": 203,
						"w": 16,
						"h": 16
					}
				},
				{
					"filename": "Barricade-YellowKey",
					"rotated": false,
					"trimmed": false,
					"sourceSize": {
						"w": 16,
						"h": 16
					},
					"spriteSourceSize": {
						"x": 0,
						"y": 0,
						"w": 16,
						"h": 16
					},
					"frame": {
						"x": 823,
						"y": 185,
						"w": 16,
						"h": 16
					}
				},
				{
					"filename": "CircleTank",
					"rotated": false,
					"trimmed": false,
					"sourceSize": {
						"w": 16,
						"h": 16
					},
					"spriteSourceSize": {
						"x": 0,
						"y": 0,
						"w": 16,
						"h": 16
					},
					"frame": {
						"x": 823,
						"y": 203,
						"w": 16,
						"h": 16
					}
				},
				{
					"filename": "CircleTankOrange",
					"rotated": false,
					"trimmed": false,
					"sourceSize": {
						"w": 16,
						"h": 16
					},
					"spriteSourceSize": {
						"x": 0,
						"y": 0,
						"w": 16,
						"h": 16
					},
					"frame": {
						"x": 841,
						"y": 185,
						"w": 16,
						"h": 16
					}
				},
				{
					"filename": "CircleTankRed",
					"rotated": false,
					"trimmed": false,
					"sourceSize": {
						"w": 16,
						"h": 16
					},
					"spriteSourceSize": {
						"x": 0,
						"y": 0,
						"w": 16,
						"h": 16
					},
					"frame": {
						"x": 841,
						"y": 203,
						"w": 16,
						"h": 16
					}
				},
				{
					"filename": "TankTurquoise",
					"rotated": false,
					"trimmed": false,
					"sourceSize": {
						"w": 16,
						"h": 16
					},
					"spriteSourceSize": {
						"x": 0,
						"y": 0,
						"w": 16,
						"h": 16
					},
					"frame": {
						"x": 859,
						"y": 185,
						"w": 16,
						"h": 16
					}
				},
				{
					"filename": "corpse",
					"rotated": false,
					"trimmed": false,
					"sourceSize": {
						"w": 16,
						"h": 16
					},
					"spriteSourceSize": {
						"x": 0,
						"y": 0,
						"w": 16,
						"h": 16
					},
					"frame": {
						"x": 859,
						"y": 203,
						"w": 16,
						"h": 16
					}
				},
				{
					"filename": "BlackKey",
					"rotated": false,
					"trimmed": false,
					"sourceSize": {
						"w": 9,
						"h": 6
					},
					"spriteSourceSize": {
						"x": 0,
						"y": 0,
						"w": 9,
						"h": 6
					},
					"frame": {
						"x": 331,
						"y": 127,
						"w": 9,
						"h": 6
					}
				},
				{
					"filename": "BlueKey",
					"rotated": false,
					"trimmed": false,
					"sourceSize": {
						"w": 9,
						"h": 6
					},
					"spriteSourceSize": {
						"x": 0,
						"y": 0,
						"w": 9,
						"h": 6
					},
					"frame": {
						"x": 1001,
						"y": 73,
						"w": 9,
						"h": 6
					}
				},
				{
					"filename": "DarkBlueKey",
					"rotated": false,
					"trimmed": false,
					"sourceSize": {
						"w": 9,
						"h": 6
					},
					"spriteSourceSize": {
						"x": 0,
						"y": 0,
						"w": 9,
						"h": 6
					},
					"frame": {
						"x": 537,
						"y": 232,
						"w": 9,
						"h": 6
					}
				},
				{
					"filename": "GreyKey",
					"rotated": false,
					"trimmed": false,
					"sourceSize": {
						"w": 9,
						"h": 6
					},
					"spriteSourceSize": {
						"x": 0,
						"y": 0,
						"w": 9,
						"h": 6
					},
					"frame": {
						"x": 342,
						"y": 127,
						"w": 9,
						"h": 6
					}
				},
				{
					"filename": "LightBlueKey",
					"rotated": false,
					"trimmed": false,
					"sourceSize": {
						"w": 9,
						"h": 6
					},
					"spriteSourceSize": {
						"x": 0,
						"y": 0,
						"w": 9,
						"h": 6
					},
					"frame": {
						"x": 1001,
						"y": 81,
						"w": 9,
						"h": 6
					}
				},
				{
					"filename": "OrangeKey",
					"rotated": false,
					"trimmed": false,
					"sourceSize": {
						"w": 9,
						"h": 6
					},
					"spriteSourceSize": {
						"x": 0,
						"y": 0,
						"w": 9,
						"h": 6
					},
					"frame": {
						"x": 548,
						"y": 232,
						"w": 9,
						"h": 6
					}
				},
				{
					"filename": "PinkKey",
					"rotated": false,
					"trimmed": false,
					"sourceSize": {
						"w": 9,
						"h": 6
					},
					"spriteSourceSize": {
						"x": 0,
						"y": 0,
						"w": 9,
						"h": 6
					},
					"frame": {
						"x": 353,
						"y": 127,
						"w": 9,
						"h": 6
					}
				},
				{
					"filename": "PurpleKey",
					"rotated": false,
					"trimmed": false,
					"sourceSize": {
						"w": 9,
						"h": 6
					},
					"spriteSourceSize": {
						"x": 0,
						"y": 0,
						"w": 9,
						"h": 6
					},
					"frame": {
						"x": 559,
						"y": 232,
						"w": 9,
						"h": 6
					}
				},
				{
					"filename": "RedKey",
					"rotated": false,
					"trimmed": false,
					"sourceSize": {
						"w": 9,
						"h": 6
					},
					"spriteSourceSize": {
						"x": 0,
						"y": 0,
						"w": 9,
						"h": 6
					},
					"frame": {
						"x": 769,
						"y": 221,
						"w": 9,
						"h": 6
					}
				},
				{
					"filename": "TurquoiseKey",
					"rotated": false,
					"trimmed": false,
					"sourceSize": {
						"w": 9,
						"h": 6
					},
					"spriteSourceSize": {
						"x": 0,
						"y": 0,
						"w": 9,
						"h": 6
					},
					"frame": {
						"x": 780,
						"y": 221,
						"w": 9,
						"h": 6
					}
				},
				{
					"filename": "YellowKey",
					"rotated": false,
					"trimmed": false,
					"sourceSize": {
						"w": 9,
						"h": 6
					},
					"spriteSourceSize": {
						"x": 0,
						"y": 0,
						"w": 9,
						"h": 6
					},
					"frame": {
						"x": 791,
						"y": 221,
						"w": 9,
						"h": 6
					}
				}
			]
		}
	],
	"meta": {
		"app": "https://www.codeandweb.com/texturepacker",
		"version": "3.0",
		"smartupdate": "$TexturePacker:SmartUpdate:c863dbe656c99f6913007a265a76346b:55461db903d92c4d3258e85e2af48019:01bd61073ce0ee21c5bb2be67683edc1$"
	}
}
